LICENSE
how_about_no/__init__.py
how_about_no/core/__init__.py
how_about_no/core/config.py
how_about_no/core/engine.py
how_about_no/core/logger.py
how_about_no/core/plugin.py
how_about_no/core/vcs.py
how_about_no/plugins/__init__.py
how_about_no/plugins/ci/__init__.py
how_about_no/plugins/ci/teamcity.py
how_about_no/plugins/vcs/__init__.py
how_about_no/plugins/vcs/changed_files.py
how_about_no/tests/__init__.py
how_about_no/tests/base_tests.py
how_about_no/tests/conftest.py
how_about_no/tests/data.py
how_about_no/tests/fakes.py
how_about_no/tests/test_core/__init__.py
how_about_no/tests/test_core/test_config.py
how_about_no/tests/test_core/test_engine.py
how_about_no/tests/test_core/test_logger.py
how_about_no/tests/test_core/test_plugin.py
how_about_no/tests/test_plugins/__init__.py
how_about_no/tests/test_plugins/test_ci/__init__.py
how_about_no/tests/test_plugins/test_ci/test_teamcity.py
how_about_no/tests/test_plugins/test_vcs/__init__.py
how_about_no/tests/test_plugins/test_vcs/test_changed_files.py
how_about_no/tests/test_vcs/__init__.py
how_about_no/tests/test_vcs/test_git.py
how_about_no/vcs/__init__.py
how_about_no/vcs/git.py
how_about_no-0.1.0b2.dist-info/entry_points.txt
how_about_no-0.1.0b2.dist-info/LICENSE
how_about_no-0.1.0b2.dist-info/WHEEL
how_about_no-0.1.0b2.dist-info/METADATA
how_about_no-0.1.0b2.dist-info/RECORD
